examples/__init__.py
examples/cdr.py
examples/natel.py
reggie/__init__.py
reggie/core.py
reggie_dsl-0.1a5.dist-info/LICENSE
reggie_dsl-0.1a5.dist-info/METADATA
reggie_dsl-0.1a5.dist-info/WHEEL
reggie_dsl-0.1a5.dist-info/top_level.txt
reggie_dsl-0.1a5.dist-info/RECORD
